LICENSE
MANIFEST.in
README.rst
pubchempy.py
setup.py
PubChemPy.egg-info/PKG-INFO
PubChemPy.egg-info/SOURCES.txt
PubChemPy.egg-info/dependency_links.txt
PubChemPy.egg-info/requires.txt
PubChemPy.egg-info/top_level.txt
docs/.DS_Store
docs/Makefile
docs/README.rst
docs/source/api.rst
docs/source/conf.py
docs/source/index.rst
docs/source/guide/advanced.rst
docs/source/guide/compound.rst
docs/source/guide/contribute.rst
docs/source/guide/download.rst
docs/source/guide/gettingstarted.rst
docs/source/guide/install.rst
docs/source/guide/introduction.rst
docs/source/guide/pandas.rst
docs/source/guide/properties.rst
docs/source/guide/searching.rst
docs/source/guide/substance.rst
requirements/common.txt
requirements/dev.txt